ercaspy/__init__.py
ercaspy/client.py
ercaspy/exceptions.py
ercaspy/models.py
ercaspy/setup.py
ercaspy/test_call.py
ercaspy/utils.py
ercaspysdk-0.2.2.dist-info/METADATA
ercaspysdk-0.2.2.dist-info/WHEEL
ercaspysdk-0.2.2.dist-info/top_level.txt
ercaspysdk-0.2.2.dist-info/RECORD
