Metadata-Version: 2.1
Name: ercaspysdk
Version: 0.2.2
Summary: A Python SDK for interacting with the Ercaspay payment gateway.
Home-page: https://github.com/brightsheden/ercaspay_python_sdk
Author: Shedenbright
Author-email: shedenbright@gmail.com
Classifier: Programming Language :: Python :: 3
Classifier: License :: OSI Approved :: MIT License
Classifier: Operating System :: OS Independent
Requires-Python: >=3.7
Requires-Dist: requests>=2.25.1
Requires-Dist: pydantic>=1.10.0
